[{"highway": "tertiary", "width": 8, "name": "Carl Avenue", "points": [[-6398.77, 46462.85], [-6341.35, 46872.33], [-6338.11, 46899.87], [-6335.87, 46928.04], [-6337.21, 46961.95], [-6339.56, 46982.64], [-6345.47, 47007.4]]}, {"highway": "secondary", "width": 10, "name": "Plain Street", "points": [[-6501.79, 46506.71], [-6482.9, 46498.25]]}, {"highway": "residential", "width": 7, "name": "Flint Road", "points": [[-6041.04, 46562.04], [-6040.79, 46571.72], [-6049.94, 46716.44]]}, {"highway": "residential", "width": 7, "name": "Grinnell Road", "points": [[-6195.54, 46875.74], [-6087.63, 46871.17], [-5984.46, 46887.98]]}, {"highway": "residential", "width": 7, "name": "Dondi Road", "points": [[-6087.63, 46871.17], [-6083.6, 47017.34]]}, {"highway": "residential", "width": 7, "name": "Schultz Road", "points": [[-6134.33, 46502.05], [-6132.46, 46510.15], [-6132.46, 46522.19], [-6133.63, 46555.74]]}, {"highway": "residential", "width": 7, "name": "Sinclair Road", "points": [[-6187.05, 47096.15], [-6195.54, 46875.74], [-6196.79, 46795.81], [-6200.36, 46717.89], [-6203.27, 46639.07], [-6202.61, 46592.76], [-6191.71, 46572.39], [-6168.08, 46557.59], [-6133.63, 46555.74], [-6041.04, 46562.04], [-6006.09, 46562.04]]}, {"highway": "residential", "width": 7, "name": "Ithica Road", "points": [[-6200.36, 46717.89], [-6049.94, 46716.44], [-5965.49, 46730.47]]}, {"highway": "residential", "width": 7, "name": "Deanna Road", "points": [[-6196.79, 46795.81], [-6073.57, 46792.36], [-5938.29, 46811.28]]}, {"highway": "residential", "width": 7, "name": "Tufts Circle", "points": [[-6203.27, 46639.07], [-6127.8, 46636.92]]}, {"highway": "service", "width": 4.5, "name": null, "points": [[-6319.22, 46499.0], [-6315.19, 46538.26], [-6315.28, 46542.45], [-6318.33, 46546.54], [-6326.39, 46548.24], [-6330.97, 46547.88], [-6333.66, 46544.94], [-6338.31, 46508.88], [-6337.51, 46504.88], [-6335.44, 46502.12], [-6331.86, 46500.51]]}, {"highway": "residential", "width": 7, "name": "Deanna Road", "points": [[-6196.79, 46795.81], [-6073.57, 46792.36], [-5938.29, 46811.28]]}]