[{"highway": "motorway", "width": 16, "name": "Amvets Highway", "points": [[-9302.92, 31965.87], [-9327.46, 31909.1], [-9385.28, 31776.29], [-9415.98, 31707.28], [-9470.31, 31582.37], [-9514.32, 31480.41]]}, {"highway": "motorway", "width": 16, "name": "Amvets Highway", "points": [[-9471.48, 31545.48], [-9247.95, 32069.98]]}, {"highway": "motorway", "width": 16, "name": "Amvets Highway", "points": [[-9302.92, 31965.87], [-9327.46, 31909.1], [-9385.28, 31776.29], [-9415.98, 31707.28], [-9470.31, 31582.37], [-9514.32, 31480.41]]}, {"highway": "motorway", "width": 16, "name": "Amvets Highway", "points": [[-9471.48, 31545.48], [-9247.95, 32069.98]]}]