[{"highway": "tertiary", "width": 8, "name": "Central Street", "points": [[-14982.55, 84213.08], [-14979.19, 84220.88], [-14976.63, 84225.68], [-14924.75, 84323.11], [-14899.37, 84370.63], [-14854.51, 84457.95], [-14844.1, 84477.55], [-14827.78, 84509.07]]}, {"highway": "tertiary", "width": 8, "name": "School Street", "points": [[-14608.06, 84020.09], [-14575.13, 84087.24], [-14573.29, 84091.02], [-14569.04, 84099.25], [-14538.09, 84159.48], [-14508.87, 84220.77], [-14505.98, 84226.17], [-14499.32, 84238.63]]}, {"highway": "secondary", "width": 10, "name": "Medford Street", "points": [[-14813.43, 83989.31], [-14847.34, 84034.24], [-14857.92, 84047.97], [-14868.89, 84062.18], [-14874.83, 84070.87], [-14878.8, 84076.67], [-14884.18, 84083.85], [-14890.28, 84089.96], [-14893.1, 84093.59], [-14934.03, 84146.12], [-14970.63, 84196.29], [-14972.68, 84199.1], [-14982.55, 84213.08], [-14987.6, 84220.28], [-14989.11, 84222.85]]}, {"highway": "secondary", "width": 10, "name": "Broadway", "points": [[-14639.8, 84398.22], [-14616.17, 84381.77], [-14604.74, 84373.76]]}, {"highway": "secondary", "width": 10, "name": "Broadway", "points": [[-14573.57, 84364.79], [-14596.08, 84380.65], [-14601.31, 84385.31]]}, {"highway": "secondary", "width": 10, "name": "Broadway", "points": [[-14788.0, 84500.96], [-14778.69, 84492.24]]}, {"highway": "secondary", "width": 10, "name": "Broadway", "points": [[-14604.74, 84373.76], [-14570.48, 84349.94], [-14540.22, 84329.02]]}, {"highway": "secondary", "width": 10, "name": "Broadway", "points": [[-14500.22, 84315.56], [-14532.4, 84338.21]]}, {"highway": "secondary", "width": 10, "name": "Broadway", "points": [[-14679.25, 84441.71], [-14701.07, 84455.76], [-14713.58, 84463.69], [-14716.75, 84465.7]]}, {"highway": "secondary", "width": 10, "name": "Broadway", "points": [[-14540.22, 84329.02], [-14484.34, 84289.8]]}, {"highway": "secondary", "width": 10, "name": "Broadway", "points": [[-14541.99, 84344.86], [-14557.09, 84355.18], [-14573.57, 84364.79]]}, {"highway": "secondary", "width": 10, "name": "Broadway", "points": [[-14532.4, 84338.21], [-14533.82, 84339.16], [-14541.99, 84344.86]]}, {"highway": "secondary", "width": 10, "name": "Broadway", "points": [[-14742.2, 84468.27], [-14723.57, 84454.68], [-14688.27, 84431.53], [-14648.57, 84404.69]]}, {"highway": "secondary", "width": 10, "name": "Broadway", "points": [[-14750.37, 84483.89], [-14775.19, 84498.13], [-14788.0, 84500.96]]}, {"highway": "tertiary", "width": 8, "name": "Main Street", "points": [[-14737.24, 84476.77], [-14742.2, 84468.27]]}, {"highway": "secondary", "width": 10, "name": "Broadway", "points": [[-14754.21, 84476.38], [-14742.2, 84468.27]]}, {"highway": "secondary", "width": 10, "name": "Broadway", "points": [[-14601.31, 84385.31], [-14609.59, 84392.65], [-14663.24, 84430.23]]}, {"highway": "secondary", "width": 10, "name": "Broadway", "points": [[-14778.69, 84492.24], [-14761.61, 84481.17], [-14756.51, 84477.88], [-14754.21, 84476.38]]}, {"highway": "secondary", "width": 10, "name": "Broadway", "points": [[-14737.24, 84476.77], [-14750.37, 84483.89]]}, {"highway": "tertiary", "width": 8, "name": "Main Street", "points": [[-14737.64, 84500.37], [-14739.58, 84495.32], [-14740.53, 84492.94], [-14741.62, 84490.59], [-14738.12, 84479.98], [-14737.24, 84476.77]]}, {"highway": "tertiary", "width": 8, "name": "Main Street", "points": [[-14737.24, 84476.77], [-14734.71, 84477.7], [-14726.09, 84480.85]]}, {"highway": "secondary", "width": 10, "name": "Broadway", "points": [[-14716.75, 84465.7], [-14737.24, 84476.77]]}, {"highway": "secondary", "width": 10, "name": "Broadway", "points": [[-14663.24, 84430.23], [-14679.25, 84441.71]]}, {"highway": "tertiary", "width": 8, "name": "Main Street", "points": [[-14716.75, 84465.7], [-14726.09, 84480.85]]}, {"highway": "secondary", "width": 10, "name": "Broadway", "points": [[-14648.57, 84404.69], [-14639.8, 84398.22]]}, {"highway": "tertiary", "width": 8, "name": "Central Street", "points": [[-14992.61, 84191.84], [-14987.86, 84200.71], [-14982.55, 84213.08]]}, {"highway": "tertiary", "width": 8, "name": "Main Street", "points": [[-14726.09, 84480.85], [-14737.64, 84500.37]]}]