[{"highway": "secondary", "width": 10, "name": "American Legion Highway", "points": [[-15990.44, 72138.99], [-16001.62, 72128.31]]}, {"highway": "secondary", "width": 10, "name": "American Legion Highway", "points": [[-15757.78, 72326.27], [-15749.57, 72333.0], [-15731.66, 72347.65], [-15699.38, 72373.81], [-15648.96, 72413.44], [-15643.88, 72418.11], [-15614.6, 72441.94], [-15613.47, 72442.85], [-15609.11, 72446.39], [-15581.81, 72468.1], [-15545.29, 72497.06], [-15539.06, 72502.28]]}, {"highway": "secondary", "width": 10, "name": "American Legion Highway", "points": [[-15994.36, 72119.35], [-15982.14, 72130.65]]}, {"highway": "secondary", "width": 10, "name": "American Legion Highway", "points": [[-15792.56, 72298.44], [-15757.78, 72326.27]]}, {"highway": "secondary", "width": 10, "name": "American Legion Highway", "points": [[-15727.51, 72366.89], [-15749.63, 72347.31], [-15754.57, 72343.75], [-15762.77, 72337.85]]}, {"highway": "secondary", "width": 10, "name": "American Legion Highway", "points": [[-15565.51, 72496.37], [-15598.43, 72469.18], [-15603.78, 72464.76], [-15663.17, 72417.12], [-15675.67, 72407.09], [-15726.25, 72368.02], [-15727.51, 72366.89]]}, {"highway": "secondary", "width": 10, "name": "American Legion Highway", "points": [[-15762.77, 72337.85], [-15803.54, 72303.79], [-15805.84, 72301.88], [-15811.35, 72297.31]]}, {"highway": "secondary", "width": 10, "name": "American Legion Highway", "points": [[-15955.31, 72171.53], [-15973.68, 72154.51], [-15990.44, 72138.99]]}, {"highway": "secondary", "width": 10, "name": "American Legion Highway", "points": [[-15811.35, 72297.31], [-15827.87, 72283.59]]}, {"highway": "secondary", "width": 10, "name": "American Legion Highway", "points": [[-15858.54, 72257.63], [-15909.29, 72214.17], [-15955.31, 72171.53]]}, {"highway": "secondary_link", "width": 6, "name": null, "points": [[-15990.44, 72138.99], [-15982.14, 72130.65]]}, {"highway": "secondary", "width": 10, "name": "American Legion Highway", "points": [[-15982.14, 72130.65], [-15929.0, 72179.89], [-15915.16, 72192.27], [-15875.84, 72227.42], [-15853.38, 72248.02]]}, {"highway": "secondary", "width": 10, "name": "American Legion Highway", "points": [[-15851.18, 72249.83], [-15816.6, 72278.29], [-15815.01, 72279.63]]}, {"highway": "secondary", "width": 10, "name": "American Legion Highway", "points": [[-15815.01, 72279.63], [-15792.56, 72298.44]]}, {"highway": "secondary", "width": 10, "name": "American Legion Highway", "points": [[-15853.38, 72248.02], [-15851.18, 72249.83]]}, {"highway": "secondary", "width": 10, "name": "American Legion Highway", "points": [[-15827.87, 72283.59], [-15839.48, 72273.95], [-15858.54, 72257.63]]}]