[{"highway": "residential", "width": 7, "name": "Donald Street", "points": [[-1804.74, -2532.86], [-1807.68, -2456.1], [-1808.15, -2443.6], [-1808.28, -2436.95], [-1808.32, -2434.46], [-1808.32, -2434.01], [-1808.7, -2419.82], [-1811.31, -2322.91], [-1810.56, -2256.57]]}, {"highway": "tertiary", "width": 8, "name": "Sharp Street", "points": [[-2001.25, -2053.56], [-1996.91, -2054.4], [-1992.31, -2055.71], [-1983.69, -2058.16], [-1973.45, -2060.36], [-1964.61, -2062.0], [-1956.38, -2062.93], [-1948.74, -2063.19], [-1843.53, -2066.41]]}, {"highway": "residential", "width": 7, "name": "West Wordell Street", "points": [[-1982.12, -2263.14], [-1947.09, -2266.25]]}, {"highway": "residential", "width": 7, "name": "McCabe Street", "points": [[-1983.7, -2187.33], [-1962.48, -2187.22], [-1913.48, -2186.21], [-1853.66, -2187.55], [-1787.85, -2188.77], [-1740.51, -2189.66], [-1693.09, -2189.55], [-1675.7, -2188.89], [-1670.13, -2188.46], [-1664.39, -2187.97], [-1657.89, -2186.54], [-1645.37, -2180.29]]}, {"highway": "residential", "width": 7, "name": "Stephen Street", "points": [[-1545.79, -2651.87], [-1557.85, -2252.67], [-1558.29, -2238.22]]}, {"highway": "residential", "width": 7, "name": "Grant Street", "points": [[-1981.95, -2308.33], [-1982.12, -2263.14]]}, {"highway": "residential", "width": 7, "name": "Grant Street", "points": [[-1982.12, -2263.14], [-1983.7, -2187.33], [-1985.36, -2125.43], [-1991.53, -2065.74], [-1991.72, -2063.88], [-1992.31, -2055.71], [-1992.77, -2043.82], [-1992.98, -2040.62], [-1997.51, -1970.48]]}, {"highway": "residential", "width": 7, "name": "Kraseman Street", "points": [[-1985.36, -2125.43], [-1913.15, -2126.77], [-1833.19, -2129.22], [-1743.41, -2133.54]]}, {"highway": "residential", "width": 7, "name": "Faith Street", "points": [[-1810.56, -2256.57], [-1766.64, -2254.68], [-1728.11, -2253.67], [-1690.68, -2253.12], [-1657.98, -2251.34], [-1627.58, -2250.91]]}, {"highway": "residential", "width": 7, "name": "Stackhouse Street", "points": [[-1616.94, -2627.56], [-1627.58, -2250.91], [-1628.96, -2201.81], [-1629.27, -2190.72]]}, {"highway": "residential", "width": 7, "name": "Stackhouse Street", "points": [[-1629.27, -2190.72], [-1629.42, -2188.72], [-1630.18, -2178.35], [-1630.16, -2174.52], [-1630.33, -2165.2], [-1631.69, -2093.37], [-1633.27, -2023.02]]}, {"highway": "tertiary", "width": 8, "name": "Sharp Street", "points": [[-1843.53, -2066.41], [-1763.7, -2068.17], [-1755.11, -2068.26]]}, {"highway": "residential", "width": 7, "name": "Bank Street", "points": [[-1707.69, -2138.25], [-1706.35, -2134.04], [-1705.41, -2130.49], [-1704.93, -2127.58], [-1704.81, -2123.69], [-1706.32, -2057.19], [-1707.56, -2016.23]]}, {"highway": "residential", "width": 7, "name": "Field Street", "points": [[-1518.78, -2045.17], [-1518.0, -2027.59], [-1509.97, -2000.52]]}, {"highway": "residential", "width": 7, "name": "Stephen Street", "points": [[-1558.29, -2238.22], [-1558.98, -2228.11], [-1561.38, -2093.15], [-1562.13, -2015.34]]}, {"highway": "secondary", "width": 10, "name": "Rockdale Avenue", "points": [[-1792.31, -1997.9], [-1755.11, -2068.26], [-1729.95, -2112.91], [-1725.78, -2119.23], [-1719.74, -2126.65], [-1717.26, -2129.22], [-1712.59, -2134.05], [-1707.69, -2138.25], [-1701.56, -2142.7], [-1683.19, -2155.24], [-1645.37, -2180.29], [-1630.83, -2189.72], [-1629.27, -2190.72], [-1596.55, -2212.01], [-1558.29, -2238.22], [-1522.53, -2261.42], [-1512.71, -2267.96], [-1495.44, -2279.35]]}, {"highway": "service", "width": 4.5, "name": null, "points": [[-1511.22, -2302.33], [-1502.05, -2311.07], [-1498.25, -2313.84]]}, {"highway": "service", "width": 4.5, "name": null, "points": [[-1503.92, -2345.06], [-1511.11, -2364.88], [-1511.32, -2373.19], [-1509.06, -2381.49]]}, {"highway": "service", "width": 4.5, "name": null, "points": [[-1512.71, -2267.96], [-1511.22, -2287.88]]}, {"highway": "residential", "width": 7, "name": "Hope Street", "points": [[-1808.15, -2443.6], [-1746.9, -2441.36], [-1720.57, -2440.39]]}, {"highway": "service", "width": 4.5, "name": null, "points": [[-1522.53, -2261.42], [-1519.77, -2254.71], [-1518.1, -2248.68], [-1517.87, -2242.98], [-1518.32, -2232.65], [-1519.94, -2153.94]]}, {"highway": "service", "width": 4.5, "name": null, "points": [[-1808.7, -2419.82], [-1831.46, -2421.22], [-1851.29, -2422.43], [-1892.86, -2423.92], [-1897.62, -2425.82], [-1902.12, -2428.68], [-1904.97, -2432.62], [-1904.72, -2453.04]]}, {"highway": "service", "width": 4.5, "name": null, "points": [[-1851.29, -2422.43], [-1851.62, -2452.68], [-1850.96, -2456.11], [-1847.86, -2458.87], [-1829.09, -2460.42], [-1825.12, -2458.76], [-1823.13, -2456.88], [-1821.14, -2456.32], [-1807.68, -2456.1]]}, {"highway": "service", "width": 4.5, "name": null, "points": [[-1831.46, -2421.22], [-1830.22, -2434.54], [-1828.78, -2436.51], [-1808.28, -2436.95]]}, {"highway": "service", "width": 4.5, "name": null, "points": [[-1746.9, -2441.36], [-1748.48, -2491.32]]}, {"highway": "service", "width": 4.5, "name": null, "points": [[-1810.56, -2256.57], [-1824.08, -2256.51], [-1859.7, -2256.67]]}, {"highway": "service", "width": 4.5, "name": null, "points": [[-1502.4, -2416.52], [-1504.47, -2436.88], [-1503.0, -2448.34], [-1499.66, -2457.42]]}, {"highway": "residential", "width": 7, "name": "Kraseman Street", "points": [[-1743.41, -2133.54], [-1728.93, -2134.14], [-1725.82, -2133.71], [-1722.91, -2132.75], [-1720.14, -2131.46], [-1717.26, -2129.22]]}, {"highway": "service", "width": 4.5, "name": null, "points": [[-1495.44, -2279.35], [-1511.22, -2287.88], [-1511.22, -2302.33], [-1511.22, -2326.81], [-1504.61, -2331.34], [-1498.82, -2333.28]]}, {"highway": "service", "width": 4.5, "name": null, "points": [[-1503.92, -2345.06], [-1504.61, -2331.34]]}, {"highway": "service", "width": 4.5, "name": null, "points": [[-1596.55, -2212.01], [-1598.12, -2170.03], [-1603.28, -2167.23], [-1609.44, -2164.78], [-1630.33, -2165.2]]}]